assemblit/__init__.py
assemblit/setup.py
assemblit/_app/__init__.py
assemblit/_app/layer.py
assemblit/_app/_generic/__init__.py
assemblit/_app/aaas/__init__.py
assemblit/_app/cli/__init__.py
assemblit/_app/cli/assemblit.py
assemblit/_app/cli/commands.py
assemblit/_app/scripts/demo.py
assemblit/_app/wiki/__init__.py
assemblit/_auth/__init__.py
assemblit/_auth/vault.py
assemblit/_database/__init__.py
assemblit/_database/_adapters.py
assemblit/_database/_datatypes.py
assemblit/_database/_generic.py
assemblit/_database/_structures.py
assemblit/_database/_syntax.py
assemblit/_database/analysis.py
assemblit/_database/data.py
assemblit/_database/sessions.py
assemblit/_database/users.py
assemblit/_orchestrator/__init__.py
assemblit/_orchestrator/layer.py
assemblit/_orchestrator/setup.py
assemblit/_orchestrator/status.py
assemblit/_orchestrator/cli/__init__.py
assemblit/_orchestrator/cli/commands.py
assemblit/_orchestrator/cli/orchestrator.py
assemblit/_orchestrator/prefect/__init__.py
assemblit/blocks/__init__.py
assemblit/blocks/structures.py
assemblit/pages/__init__.py
assemblit/pages/account_settings.py
assemblit/pages/code_documentation.py
assemblit/pages/data_ingestion.py
assemblit/pages/home.py
assemblit/pages/run_analysis.py
assemblit/pages/run_listing.py
assemblit/pages/session_selector.py
assemblit/pages/workflow_settings.py
assemblit/pages/_components/__init__.py
assemblit/pages/_components/_core.py
assemblit/pages/_components/_data_review.py
assemblit/pages/_components/_data_uploader.py
assemblit/pages/_components/_key_value.py
assemblit/pages/_components/_run_analysis.py
assemblit/pages/_components/_run_listing.py
assemblit/pages/_components/_selector.py
assemblit/toolkit/__init__.py
assemblit/toolkit/_dataframe.py
assemblit/toolkit/_exceptions.py
assemblit/toolkit/_yaml.py
assemblit/toolkit/aggregator.py
assemblit/toolkit/content.py
assemblit/toolkit/plotter.py
tests/__init__.py
tests/test_app_layer.py
tests/test_blocks.py
tests/test_toolkit.py
assemblit-0.1.13.dist-info/LICENSE
assemblit-0.1.13.dist-info/METADATA
assemblit-0.1.13.dist-info/WHEEL
assemblit-0.1.13.dist-info/entry_points.txt
assemblit-0.1.13.dist-info/top_level.txt
assemblit-0.1.13.dist-info/RECORD
