Metadata-Version: 2.1
Name: assemblit
Version: 0.1.13
Summary: Assemblit is helping data analysts and scientists rapidly scale notebooks into analytics-as-a-service (AaaS) web-applications.
Home-page: https://assemblit.org
Author: Tom Eleff
Project-URL: Issues, https://github.com/thomaseleff/assemblit/issues
Project-URL: Releases, https://github.com/thomaseleff/assemblit/releases
Classifier: Development Status :: 4 - Beta
Classifier: Topic :: Database :: Front-Ends
Classifier: License :: OSI Approved :: MIT License
Classifier: Programming Language :: Python :: 3.8
Classifier: Programming Language :: Python :: 3.9
Classifier: Programming Language :: Python :: 3.10
Classifier: Programming Language :: Python :: 3.11
Classifier: Programming Language :: Python :: 3.12
Requires-Python: >=3.8.0
License-File: LICENSE
Requires-Dist: streamlit ==1.37.0
Requires-Dist: prefect ==2.16.6
Requires-Dist: regex ==2023.10.3
Requires-Dist: argon2-cffi ==23.1.0
Requires-Dist: email-validator ==2.1.0.post1
Requires-Dist: pandas >=2.0.3
Requires-Dist: pandera ==0.20.3
Requires-Dist: plotly ==5.23.0
Requires-Dist: python-dotenv ==1.0.0
Requires-Dist: pytensils ==1.2.0
Requires-Dist: pyyaml ==6.0.1
